setup.py
django_bootstrap_tags/__init__.py
django_bootstrap_tags/admin.py
django_bootstrap_tags/fields.py
django_bootstrap_tags/models.py
django_bootstrap_tags/widgets.py
django_bootstrap_tags.egg-info/PKG-INFO
django_bootstrap_tags.egg-info/SOURCES.txt
django_bootstrap_tags.egg-info/dependency_links.txt
django_bootstrap_tags.egg-info/not-zip-safe
django_bootstrap_tags.egg-info/requires.txt
django_bootstrap_tags.egg-info/top_level.txt
django_bootstrap_tags/static/css/bootstrap-tags.css
django_bootstrap_tags/static/js/bootstrap-tags.js
django_bootstrap_tags/static/js/bootstrap3-typeahead.min.js