Metadata-Version: 1.0
Name: django-bootstrap-tags
Version: 1.2.0
Summary: A django form widget and tag model to add typeahead tagging to any form.
Home-page: http://thegoods.aj7may.com/django-bootstrap-tags
Author: A.J. May
Author-email: aj7may@gmail.com
License: Creative Commons Attribution-ShareAlike 4.0 International License
Keywords: django bootstrap tags tagging form widget typeahead
Platform: UNKNOWN
